t3dn_bip/__init__.py
t3dn_bip/formats.py
t3dn_bip/ops.py
t3dn_bip/previews.py
t3dn_bip/settings.py
t3dn_bip/threads.py
t3dn_bip/utils.py
t3dn_bip-1.0.9.dist-info/METADATA
t3dn_bip-1.0.9.dist-info/WHEEL
t3dn_bip-1.0.9.dist-info/top_level.txt
t3dn_bip-1.0.9.dist-info/RECORD
