Metadata-Version: 2.1
Name: t3dn-bip
Version: 1.0.9
Summary: 3DN BIP allows blazingly fast image loads in Blender.
Home-page: https://github.com/3dninjas/3dn-bip
Author: 3D Ninjas GmbH
Author-email: niklas@3dninjas.io
License: GPLv3
Platform: UNKNOWN
Classifier: Programming Language :: Python
Classifier: License :: OSI Approved :: GNU General Public License v3 (GPLv3)
Classifier: Operating System :: OS Independent
